{
 "gameId": "6480062",
 "date": "2025-11-15",
 "info": {
  "contests": [
   {
    "__typename": "Contest",
    "id": "6480062",
    "sportCode": "WVB",
    "sportUrl": "volleyball-women",
    "division": 1,
    "clock": null,
    "currentPeriod": "FINAL",
    "finalMessage": "FINAL",
    "gameState": "F",
    "statusCodeDisplay": "final",
    "network": null,
    "startTime": "14:00",
    "startTimeEpoch": 1763233200,
    "week": null,
    "seasonYear": 2025,
    "winner": 46422,
    "hasStartTime": true,
    "hasBoxscore": true,
    "hasPbp": true,
    "hasScoringSummary": false,
    "hasPreview": false,
    "hasRecap": false,
    "hasTeamStats": true,
    "linescores": [
     {
      "__typename": "Linescore",
      "period": "1",
      "home": "22",
      "visit": "25"
     },
     {
      "__typename": "Linescore",
      "period": "2",
      "home": "20",
      "visit": "25"
     },
     {
      "__typename": "Linescore",
      "period": "3",
      "home": "24",
      "visit": "26"
     }
    ],
    "teams": [
     {
      "__typename": "ContestTeam",
      "teamId": "46557",
      "isHome": true,
      "color": "#582C83",
      "seoname": "kansas-st",
      "nameFull": "Kansas State University",
      "nameShort": "Kansas St.",
      "name6Char": "KAN ST",
      "teamRank": null,
      "gameRank": null,
      "score": 0,
      "seed": null,
      "record": "(15-7)",
      "divisionName": "d1",
      "division": 1,
      "isWinner": false
     },
     {
      "__typename": "ContestTeam",
      "teamId": "46422",
      "isHome": false,
      "color": "#1967B8",
      "seoname": "kansas",
      "nameFull": "University of Kansas",
      "nameShort": "Kansas",
      "name6Char": "KANSAS",
      "teamRank": 13,
      "gameRank": 13,
      "score": 3,
      "seed": null,
      "record": "(19-8)",
      "divisionName": "d1",
      "division": 1,
      "isWinner": true
     }
    ],
    "liveVideos": [],
    "championship": null,
    "championshipGame": null,
    "links": [],
    "location": null,
    "stats": null
   }
  ]
 },
 "box": {
  "__typename": "Boxscore",
  "contestId": 6480062,
  "title": "WVB Boxscore",
  "description": "Kansas St. vs Kansas",
  "sportCode": "WVB",
  "divisionName": "d1",
  "gameType": null,
  "period": "FINAL",
  "status": "F",
  "minutes": null,
  "seconds": null,
  "teams": [
   {
    "__typename": "ContestTeam",
    "isHome": true,
    "teamId": "46557",
    "seoname": "kansas-st",
    "name6Char": "KAN ST",
    "nameFull": "Kansas State University",
    "nameShort": "Kansas St.",
    "teamName": "Wildcats",
    "color": "#582C83"
   },
   {
    "__typename": "ContestTeam",
    "isHome": false,
    "teamId": "46422",
    "seoname": "kansas",
    "name6Char": "KANSAS",
    "nameFull": "University of Kansas",
    "nameShort": "Kansas",
    "teamName": "Jayhawks",
    "color": "#1967B8"
   }
  ],
  "teamBoxscore": [
   {
    "__typename": "BoxscoreDetails",
    "teamId": 46557,
    "playerStats": [
     {
      "__typename": "PlayerStatsVolleyball",
      "firstName": "Aniya",
      "lastName": "Clinton",
      "position": "OH",
      "number": 5,
      "gamesPlayed": "3",
      "ballHandlingErrors": "0",
      "points": "11.5",
      "kills": "11",
      "attackErrors": "5",
      "attackAttempts": "30",
      "hittingPercentage": "0.200",
      "assists": "0",
      "setErrors": "0",
      "setAttempts": "3",
      "serviceAces": "0",
      "serviceErrors": "0",
      "serveAttempts": "13",
      "digs": "11",
      "receptionAttempts": "13",
      "receptionErrors": "0",
      "blockSolos": "0",
      "blockAssists": "1",
      "blockingErrors": "1",
      "totalBlocks": "1",
      "starter": true,
      "participated": true
     },
     {
      "__typename": "PlayerStatsVolleyball",
      "firstName": "Reagan",
      "lastName": "Fox",
      "position": "OH",
      "number": 4,
      "gamesPlayed": "3",
      "ballHandlingErrors": "0",
      "points": "5",
      "kills": "4",
      "attackErrors": "5",
      "attackAttempts": "16",
      "hittingPercentage": "-0.063",
      "assists": "1",
      "setErrors": "0",
      "setAttempts": "4",
      "serviceAces": "0",
      "serviceErrors": "0",
      "serveAttempts": "0",
      "digs": "0",
      "receptionAttempts": "1",
      "receptionErrors": "1",
      "blockSolos": "0",
      "blockAssists": "2",
      "blockingErrors": "0",
      "totalBlocks": "2",
      "starter": false,
      "participated": true
     },
     {
      "__typename": "PlayerStatsVolleyball",
      "firstName": "Symone",
      "lastName": "Sims",
      "position": "L/DS",
      "number": 7,
      "gamesPlayed": "3",
      "ballHandlingErrors": "0",
      "points": "1",
      "kills": "0",
      "attackErrors": "1",
      "attackAttempts": "1",
      "hittingPercentage": "-1.000",
      "assists": "4",
      "setErrors": "0",
      "setAttempts": "9",
      "serviceAces": "1",
      "serviceErrors": "2",
      "serveAttempts": "11",
      "digs": "12",
      "receptionAttempts": "19",
      "receptionErrors": "0",
      "blockSolos": "0",
      "blockAssists": "0",
      "blockingErrors": "0",
      "totalBlocks": "0",
      "starter": false,
      "participated": true
     },
     {
      "__typename": "PlayerStatsVolleyball",
      "firstName": "Caleigh",
      "lastName": "Ponn",
      "position": "L/DS",
      "number": 1,
      "gamesPlayed": "3",
      "ballHandlingErrors": "0",
      "points": "0",
      "kills": "0",
      "attackErrors": "0",
      "attackAttempts": "0",
      "hittingPercentage": ".000",
      "assists": "1",
      "setErrors": "0",
      "setAttempts": "6",
      "serviceAces": "0",
      "serviceErrors": "1",
      "serveAttempts": "12",
      "digs": "9",
      "receptionAttempts": "16",
      "receptionErrors": "0",
      "blockSolos": "0",
      "blockAssists": "0",
      "blockingErrors": "0",
      "totalBlocks": "0",
      "starter": true,
      "participated": true
     },
     {
      "__typename": "PlayerStatsVolleyball",
      "firstName": "Shaylee",
      "lastName": "Myers",
      "position": "OH",
      "number": 14,
      "gamesPlayed": "3",
      "ballHandlingErrors": "0",
      "points": "15",
      "kills": "15",
      "attackErrors": "5",
      "attackAttempts": "46",
      "hittingPercentage": "0.217",
      "assists": "0",
      "setErrors": "0",
      "setAttempts": "2",
      "serviceAces": "0",
      "serviceErrors": "1",
      "serveAttempts": "10",
      "digs": "2",
      "receptionAttempts": "13",
      "receptionErrors": "0",
      "blockSolos": "0",
      "blockAssists": "0",
      "blockingErrors": "0",
      "totalBlocks": "0",
      "starter": true,
      "participated": true
     },
     {
      "__typename": "PlayerStatsVolleyball",
      "firstName": "Emerson",
      "lastName": "Van Lannen",
      "position": "S",
      "number": 13,
      "gamesPlayed": "3",
      "ballHandlingErrors": "0",
      "points": "1",
      "kills": "0",
      "attackErrors": "0",
      "attackAttempts": "0",
      "hittingPercentage": ".000",
      "assists": "0",
      "setErrors": "0",
      "setAttempts": "0",
      "serviceAces": "1",
      "serviceErrors": "1",
      "serveAttempts": "14",
      "digs": "2",
      "receptionAttempts": "0",
      "receptionErrors": "0",
      "blockSolos": "0",
      "blockAssists": "0",
      "blockingErrors": "0",
      "totalBlocks": "0",
      "starter": false,
      "participated": true
     },
     {
      "__typename": "PlayerStatsVolleyball",
      "firstName": "Ava",
      "lastName": "LeGrand",
      "position": "S",
      "number": 11,
      "gamesPlayed": "3",
      "ballHandlingErrors": "0",
      "points": "1.5",
      "kills": "1",
      "attackErrors": "1",
      "attackAttempts": "4",
      "hittingPercentage": ".000",
      "assists": "34",
      "setErrors": "0",
      "setAttempts": "100",
      "serviceAces": "0",
      "serviceErrors": "0",
      "serveAttempts": "7",
      "digs": "12",
      "receptionAttempts": "0",
      "receptionErrors": "0",
      "blockSolos": "0",
      "blockAssists": "1",
      "blockingErrors": "1",
      "totalBlocks": "1",
      "starter": true,
      "participated": true
     },
     {
      "__typename": "PlayerStatsVolleyball",
      "firstName": "Brenna",
      "lastName": "Schmidt",
      "position": "MB",
      "number": 18,
      "gamesPlayed": "3",
      "ballHandlingErrors": "0",
      "points": "4",
      "kills": "2",
      "attackErrors": "1",
      "attackAttempts": "10",
      "hittingPercentage": "0.100",
      "assists": "0",
      "setErrors": "0",
      "setAttempts": "0",
      "serviceAces": "0",
      "serviceErrors": "0",
      "serveAttempts": "0",
      "digs": "1",
      "receptionAttempts": "0",
      "receptionErrors": "0",
      "blockSolos": "0",
      "blockAssists": "4",
      "blockingErrors": "1",
      "totalBlocks": "4",
      "starter": true,
      "participated": true
     },
     {
      "__typename": "PlayerStatsVolleyball",
      "firstName": "Jordyn",
      "lastName": "Williams",
      "position": "MB",
      "number": 21,
      "gamesPlayed": "3",
      "ballHandlingErrors": "0",
      "points": "7",
      "kills": "7",
      "attackErrors": "3",
      "attackAttempts": "20",
      "hittingPercentage": "0.200",
      "assists": "0",
      "setErrors": "0",
      "setAttempts": "1",
      "serviceAces": "0",
      "serviceErrors": "0",
      "serveAttempts": "0",
      "digs": "1",
      "receptionAttempts": "1",
      "receptionErrors": "0",
      "blockSolos": "0",
      "blockAssists": "0",
      "blockingErrors": "0",
      "totalBlocks": "0",
      "starter": true,
      "participated": true
     }
    ],
    "teamStats": {
     "__typename": "TeamStatsVolleyball",
     "sets": [
      {
       "__typename": "AttackGame",
       "game": "1",
       "kills": "14",
       "attackErrors": "7",
       "attackAttempts": "40",
       "hittingPercentage": "0.175"
      },
      {
       "__typename": "AttackGame",
       "game": "2",
       "kills": "9",
       "attackErrors": "8",
       "attackAttempts": "41",
       "hittingPercentage": "0.024"
      },
      {
       "__typename": "AttackGame",
       "game": "3",
       "kills": "17",
       "attackErrors": "6",
       "attackAttempts": "46",
       "hittingPercentage": "0.239"
      }
     ],
     "gamesPlayed": "3",
     "ballHandlingErrors": "0",
     "points": "66",
     "kills": "40",
     "attackErrors": "21",
     "attackAttempts": "127",
     "hittingPercentage": "0.150",
     "assists": "40",
     "setErrors": "0",
     "setAttempts": "125",
     "serviceAces": "2",
     "serviceErrors": "5",
     "serveAttempts": "67",
     "digs": "50",
     "receptionAttempts": "67",
     "receptionErrors": "5",
     "blockSolos": "0",
     "blockAssists": "8",
     "blockingErrors": "3",
     "totalBlocks": "4"
    }
   },
   {
    "__typename": "BoxscoreDetails",
    "teamId": 46422,
    "playerStats": [
     {
      "__typename": "PlayerStatsVolleyball",
      "firstName": "Katie",
      "lastName": "Dalton",
      "position": "S",
      "number": 7,
      "gamesPlayed": "3",
      "ballHandlingErrors": "0",
      "points": "6.5",
      "kills": "4",
      "attackErrors": "1",
      "attackAttempts": "7",
      "hittingPercentage": "0.429",
      "assists": "35",
      "setErrors": "0",
      "setAttempts": "89",
      "serviceAces": "1",
      "serviceErrors": "1",
      "serveAttempts": "14",
      "digs": "8",
      "receptionAttempts": "0",
      "receptionErrors": "0",
      "blockSolos": "0",
      "blockAssists": "3",
      "blockingErrors": "1",
      "totalBlocks": "3",
      "starter": true,
      "participated": true
     },
     {
      "__typename": "PlayerStatsVolleyball",
      "firstName": "Molly",
      "lastName": "McCarthy",
      "position": "L/DS",
      "number": 19,
      "gamesPlayed": "3",
      "ballHandlingErrors": "0",
      "points": "0.5",
      "kills": "0",
      "attackErrors": "0",
      "attackAttempts": "1",
      "hittingPercentage": ".000",
      "assists": "1",
      "setErrors": "0",
      "setAttempts": "2",
      "serviceAces": "0",
      "serviceErrors": "0",
      "serveAttempts": "0",
      "digs": "7",
      "receptionAttempts": "12",
      "receptionErrors": "1",
      "blockSolos": "0",
      "blockAssists": "1",
      "blockingErrors": "0",
      "totalBlocks": "1",
      "starter": false,
      "participated": true
     },
     {
      "__typename": "PlayerStatsVolleyball",
      "firstName": "Jovana",
      "lastName": "Zelenovic",
      "position": "OH",
      "number": 9,
      "gamesPlayed": "3",
      "ballHandlingErrors": "0",
      "points": "14.5",
      "kills": "10",
      "attackErrors": "3",
      "attackAttempts": "25",
      "hittingPercentage": "0.280",
      "assists": "1",
      "setErrors": "0",
      "setAttempts": "1",
      "serviceAces": "3",
      "serviceErrors": "2",
      "serveAttempts": "12",
      "digs": "3",
      "receptionAttempts": "0",
      "receptionErrors": "0",
      "blockSolos": "0",
      "blockAssists": "3",
      "blockingErrors": "0",
      "totalBlocks": "3",
      "starter": true,
      "participated": true
     },
     {
      "__typename": "PlayerStatsVolleyball",
      "firstName": "Rhian",
      "lastName": "Swanson",
      "position": "OH",
      "number": 4,
      "gamesPlayed": "3",
      "ballHandlingErrors": "0",
      "points": "10",
      "kills": "10",
      "attackErrors": "2",
      "attackAttempts": "25",
      "hittingPercentage": "0.320",
      "assists": "0",
      "setErrors": "0",
      "setAttempts": "0",
      "serviceAces": "0",
      "serviceErrors": "0",
      "serveAttempts": "0",
      "digs": "1",
      "receptionAttempts": "0",
      "receptionErrors": "0",
      "blockSolos": "0",
      "blockAssists": "0",
      "blockingErrors": "0",
      "totalBlocks": "0",
      "starter": false,
      "participated": true
     },
     {
      "__typename": "PlayerStatsVolleyball",
      "firstName": "Selena",
      "lastName": "Leban",
      "position": "OH",
      "number": 5,
      "gamesPlayed": "1",
      "ballHandlingErrors": "0",
      "points": "1",
      "kills": "1",
      "attackErrors": "0",
      "attackAttempts": "2",
      "hittingPercentage": "0.500",
      "assists": "0",
      "setErrors": "0",
      "setAttempts": "0",
      "serviceAces": "0",
      "serviceErrors": "0",
      "serveAttempts": "0",
      "digs": "0",
      "receptionAttempts": "0",
      "receptionErrors": "0",
      "blockSolos": "0",
      "blockAssists": "0",
      "blockingErrors": "0",
      "totalBlocks": "0",
      "starter": false,
      "participated": true
     },
     {
      "__typename": "PlayerStatsVolleyball",
      "firstName": "Grace",
      "lastName": "Nelson",
      "position": "OH",
      "number": 1,
      "gamesPlayed": "3",
      "ballHandlingErrors": "0",
      "points": "7.5",
      "kills": "7",
      "attackErrors": "7",
      "attackAttempts": "29",
      "hittingPercentage": ".000",
      "assists": "2",
      "setErrors": "0",
      "setAttempts": "5",
      "serviceAces": "0",
      "serviceErrors": "1",
      "serveAttempts": "12",
      "digs": "10",
      "receptionAttempts": "26",
      "receptionErrors": "0",
      "blockSolos": "0",
      "blockAssists": "1",
      "blockingErrors": "0",
      "totalBlocks": "1",
      "starter": true,
      "participated": true
     },
     {
      "__typename": "PlayerStatsVolleyball",
      "firstName": "Ryan",
      "lastName": "White",
      "position": "L/DS",
      "number": 22,
      "gamesPlayed": "3",
      "ballHandlingErrors": "0",
      "points": "1",
      "kills": "0",
      "attackErrors": "0",
      "attackAttempts": "0",
      "hittingPercentage": ".000",
      "assists": "4",
      "setErrors": "0",
      "setAttempts": "10",
      "serviceAces": "1",
      "serviceErrors": "1",
      "serveAttempts": "15",
      "digs": "14",
      "receptionAttempts": "10",
      "receptionErrors": "0",
      "blockSolos": "0",
      "blockAssists": "0",
      "blockingErrors": "0",
      "totalBlocks": "0",
      "starter": false,
      "participated": true
     },
     {
      "__typename": "PlayerStatsVolleyball",
      "firstName": "Aisha",
      "lastName": "Aiono",
      "position": "MB",
      "number": 24,
      "gamesPlayed": "3",
      "ballHandlingErrors": "0",
      "points": "6",
      "kills": "4",
      "attackErrors": "2",
      "attackAttempts": "10",
      "hittingPercentage": "0.200",
      "assists": "0",
      "setErrors": "0",
      "setAttempts": "1",
      "serviceAces": "0",
      "serviceErrors": "0",
      "serveAttempts": "0",
      "digs": "0",
      "receptionAttempts": "1",
      "receptionErrors": "0",
      "blockSolos": "0",
      "blockAssists": "4",
      "blockingErrors": "0",
      "totalBlocks": "4",
      "starter": true,
      "participated": true
     },
     {
      "__typename": "PlayerStatsVolleyball",
      "firstName": "Logan",
      "lastName": "Bell",
      "position": "OH",
      "number": 25,
      "gamesPlayed": "3",
      "ballHandlingErrors": "0",
      "points": "0",
      "kills": "0",
      "attackErrors": "1",
      "attackAttempts": "2",
      "hittingPercentage": "-0.500",
      "assists": "0",
      "setErrors": "0",
      "setAttempts": "2",
      "serviceAces": "0",
      "serviceErrors": "0",
      "serveAttempts": "12",
      "digs": "4",
      "receptionAttempts": "11",
      "receptionErrors": "1",
      "blockSolos": "0",
      "blockAssists": "0",
      "blockingErrors": "0",
      "totalBlocks": "0",
      "starter": true,
      "participated": true
     },
     {
      "__typename": "PlayerStatsVolleyball",
      "firstName": "Cristin",
      "lastName": "Cline",
      "position": "S",
      "number": 11,
      "gamesPlayed": "1",
      "ballHandlingErrors": "0",
      "points": "0",
      "kills": "0",
      "attackErrors": "0",
      "attackAttempts": "0",
      "hittingPercentage": ".000",
      "assists": "0",
      "setErrors": "0",
      "setAttempts": "1",
      "serviceAces": "0",
      "serviceErrors": "0",
      "serveAttempts": "0",
      "digs": "0",
      "receptionAttempts": "0",
      "receptionErrors": "0",
      "blockSolos": "0",
      "blockAssists": "0",
      "blockingErrors": "0",
      "totalBlocks": "0",
      "starter": false,
      "participated": true
     },
     {
      "__typename": "PlayerStatsVolleyball",
      "firstName": "Reese",
      "lastName": "Ptacek",
      "position": "MB",
      "number": 10,
      "gamesPlayed": "3",
      "ballHandlingErrors": "0",
      "points": "11",
      "kills": "9",
      "attackErrors": "0",
      "attackAttempts": "15",
      "hittingPercentage": "0.600",
      "assists": "0",
      "setErrors": "0",
      "setAttempts": "1",
      "serviceAces": "0",
      "serviceErrors": "3",
      "serveAttempts": "10",
      "digs": "1",
      "receptionAttempts": "2",
      "receptionErrors": "0",
      "blockSolos": "1",
      "blockAssists": "2",
      "blockingErrors": "0",
      "totalBlocks": "3",
      "starter": true,
      "participated": true
     },
     {
      "__typename": "PlayerStatsVolleyball",
      "firstName": "Ellie",
      "lastName": "Schneider",
      "position": "MB",
      "number": 15,
      "gamesPlayed": "1",
      "ballHandlingErrors": "0",
      "points": "0",
      "kills": "0",
      "attackErrors": "0",
      "attackAttempts": "0",
      "hittingPercentage": ".000",
      "assists": "0",
      "setErrors": "0",
      "setAttempts": "0",
      "serviceAces": "0",
      "serviceErrors": "0",
      "serveAttempts": "0",
      "digs": "0",
      "receptionAttempts": "0",
      "receptionErrors": "0",
      "blockSolos": "0",
      "blockAssists": "0",
      "blockingErrors": "0",
      "totalBlocks": "0",
      "starter": false,
      "participated": true
     }
    ],
    "teamStats": {
     "__typename": "TeamStatsVolleyball",
     "sets": [
      {
       "__typename": "AttackGame",
       "game": "1",
       "kills": "16",
       "attackErrors": "4",
       "attackAttempts": "39",
       "hittingPercentage": "0.308"
      },
      {
       "__typename": "AttackGame",
       "game": "2",
       "kills": "12",
       "attackErrors": "8",
       "attackAttempts": "36",
       "hittingPercentage": "0.111"
      },
      {
       "__typename": "AttackGame",
       "game": "3",
       "kills": "17",
       "attackErrors": "4",
       "attackAttempts": "41",
       "hittingPercentage": "0.317"
      }
     ],
     "gamesPlayed": "3",
     "ballHandlingErrors": "0",
     "points": "76",
     "kills": "45",
     "attackErrors": "16",
     "attackAttempts": "116",
     "hittingPercentage": "0.250",
     "assists": "43",
     "setErrors": "0",
     "setAttempts": "112",
     "serviceAces": "5",
     "serviceErrors": "8",
     "serveAttempts": "75",
     "digs": "48",
     "receptionAttempts": "62",
     "receptionErrors": "2",
     "blockSolos": "1",
     "blockAssists": "14",
     "blockingErrors": "1",
     "totalBlocks": "8"
    }
   }
  ]
 }
}